torchplate/__init__.py
torchplate/experiment.py
torchplate/metrics.py
torchplate/utils.py
torchplate-0.0.10.dist-info/METADATA
torchplate-0.0.10.dist-info/WHEEL
torchplate-0.0.10.dist-info/licenses/LICENSE
torchplate-0.0.10.dist-info/RECORD
