Metadata-Version: 2.1
Name: torchplate
Version: 0.0.10
Summary: A minimal and simple machine learning experiment module for PyTorch.
Project-URL: Homepage, https://github.com/rosikand/torchplate
Author-email: Rohan Sikand <rsikand29@gmail.com>
License: Copyright (c) 2018 The Python Packaging Authority
License-File: LICENSE
Classifier: License :: OSI Approved :: MIT License
Classifier: Operating System :: OS Independent
Classifier: Programming Language :: Python :: 3
Requires-Python: >=3.7
